mergenetic/README.md
mergenetic/__init__.py
mergenetic/utils.py
mergenetic/estimator/__init__.py
mergenetic/estimator/perf_estimation.py
mergenetic/estimator/utils.py
mergenetic/evaluation/__init__.py
mergenetic/evaluation/evaluator.py
mergenetic/evaluation/lm_harness.py
mergenetic/evaluation/math_language.py
mergenetic/evaluation/multilingual_evaluator.py
mergenetic/evaluation/utils.py
mergenetic/merging/__init__.py
mergenetic/merging/dare_taskarithmetic_merger.py
mergenetic/merging/linear_merger.py
mergenetic/merging/merger.py
mergenetic/merging/slerp_merger.py
mergenetic/merging/taskarithmetic_merger.py
mergenetic/merging/ties_dare_merger.py
mergenetic/merging/ties_merger.py
mergenetic/optimization/__init__.py
mergenetic/optimization/merging_problem.py
mergenetic/optimization/predefined_problems.py
mergenetic/searcher/__init__.py
mergenetic/searcher/searcher.py
mergenetic-0.1.1.dist-info/METADATA
mergenetic-0.1.1.dist-info/WHEEL
mergenetic-0.1.1.dist-info/top_level.txt
mergenetic-0.1.1.dist-info/RECORD
