Metadata-Version: 2.4
Name: mergenetic
Version: 0.1.1
Summary: Evolutionary model merging for LLMs
Author-email: Tommaso Mencattini <tommaso.mencattini@epfl.ch>, "Adrian R. Minut" <robertadrian.minut@gmail.com>
License-Expression: Apache-2.0
Project-URL: Homepage, https://github.com/tommasomncttn/mergenetic
Project-URL: Repository, https://github.com/tommasomncttn/mergenetic.git
Project-URL: Issues, https://github.com/tommasomncttn/mergenetic/issues
Keywords: llm,model merging,evolutionary optimization,mergekit
Requires-Python: <3.12,>=3.10
Requires-Dist: accelerate==1.3.0
Requires-Dist: bitsandbytes==0.45.4
Requires-Dist: einops==0.7.0
Requires-Dist: fasttext-numpy2
Requires-Dist: git-python
Requires-Dist: gradio==5.29.1
Requires-Dist: lm-eval[vllm]==0.4.8
Requires-Dist: mergekit==0.0.6
Requires-Dist: pandas==2.2.2
Requires-Dist: plotly
Requires-Dist: psutil==7.0.0
Requires-Dist: pymoo==0.6.1.3
Requires-Dist: pyyaml==6.0.1
Requires-Dist: scikit-learn
Requires-Dist: transformers==4.45.2
Requires-Dist: wheel==0.41.2
Requires-Dist: wrapt==1.16.0
Requires-Dist: xxhash==3.4.1
Requires-Dist: yarl==1.9.4
Requires-Dist: prompt_toolkit==3.0.51
Provides-Extra: dev
Requires-Dist: pytest; extra == "dev"
Requires-Dist: flake8; extra == "dev"
Requires-Dist: black; extra == "dev"
Requires-Dist: isort; extra == "dev"
